seldom/__init__.py
seldom/appdriver.py
seldom/appium_lab/__init__.py
seldom/appium_lab/action.py
seldom/appium_lab/android.py
seldom/appium_lab/appium_service.py
seldom/appium_lab/find.py
seldom/appium_lab/keyboard.py
seldom/appium_lab/ocr_plugin.py
seldom/appium_lab/switch.py
seldom/case.py
seldom/cli.py
seldom/db_operation/__init__.py
seldom/db_operation/base_db.py
seldom/db_operation/mongo_db.py
seldom/db_operation/mssql_db.py
seldom/db_operation/mysql_db.py
seldom/db_operation/postgres_db.py
seldom/db_operation/sqlite_db.py
seldom/driver.py
seldom/extend_lib/__init__.py
seldom/extend_lib/base_assert.py
seldom/extend_lib/curlify.py
seldom/extend_lib/jsonpath.py
seldom/extend_lib/parameterized.py
seldom/extend_lib/tomorrow.py
seldom/file_runner/__init__.py
seldom/file_runner/api_excel.py
seldom/har2case/__init__.py
seldom/har2case/core.py
seldom/har2case/demo.har
seldom/har2case/demo.py
seldom/har2case/utils.py
seldom/logging/__init__.py
seldom/logging/exceptions.py
seldom/logging/log.py
seldom/project_temp/__init__.py
seldom/project_temp/api/confrun.py
seldom/project_temp/api/run.py
seldom/project_temp/api/test_sample.py
seldom/project_temp/app/confrun.py
seldom/project_temp/app/run.py
seldom/project_temp/app/test_sample.py
seldom/project_temp/data.json
seldom/project_temp/web/confrun.py
seldom/project_temp/web/run.py
seldom/project_temp/web/test_sample.py
seldom/request.py
seldom/running/__init__.py
seldom/running/config.py
seldom/running/DebugTestRunner.py
seldom/running/loader_extend.py
seldom/running/loader_hook.py
seldom/running/runner.py
seldom/skip.py
seldom/swagger2case/__init__.py
seldom/swagger2case/core.py
seldom/swagger2case/swagger.json
seldom/swagger2case/swagger.py
seldom/testdata/__init__.py
seldom/testdata/conversion.py
seldom/testdata/parameterization.py
seldom/testdata/random_data.py
seldom/testdata/random_func.py
seldom/utils/__init__.py
seldom/utils/adbutils.py
seldom/utils/benchmark.py
seldom/utils/cache.py
seldom/utils/cache_data.json
seldom-3.14.1.dist-info/entry_points.txt
seldom-3.14.1.dist-info/licenses/LICENSE
seldom-3.14.1.dist-info/METADATA
seldom-3.14.1.dist-info/WHEEL
seldom-3.14.1.dist-info/RECORD
