Metadata-Version: 2.4
Name: seldom
Version: 3.14.1
Summary: Seldom automation testing framework based on unittest.
License: Apache License
License-File: LICENSE
Keywords: seldom,selenium,appium,requests
Author: bugmaster
Author-email: fnngj@126.com
Requires-Python: >=3.9,<4.0
Classifier: Intended Audience :: Developers
Classifier: Operating System :: MacOS :: MacOS X
Classifier: Operating System :: Microsoft :: Windows
Classifier: Programming Language :: Python :: 3
Classifier: Programming Language :: Python :: 3.9
Classifier: Programming Language :: Python :: 3.10
Classifier: Programming Language :: Python :: 3.11
Classifier: Programming Language :: Python :: 3.12
Classifier: Programming Language :: Python :: 3.13
Classifier: Programming Language :: Python :: 3.14
Classifier: Topic :: Internet :: WWW/HTTP :: Dynamic Content
Classifier: Topic :: Software Development :: Testing
Requires-Dist: appium-python-client (>=5.1.0,<6.0.0)
Requires-Dist: genson (>=1.2.2,<1.3.0)
Requires-Dist: jmespath (>=0.10.0,<1.0.0)
Requires-Dist: jsonschema (>=4.10.0,<5.0.0)
Requires-Dist: loguru (>=0.7.0,<0.8.0)
Requires-Dist: openpyxl (>=3.0.3,<4.0.0)
Requires-Dist: pycryptodome (>=3.21.0,<4.0.0)
Requires-Dist: pymysql (>=1.0.0,<2.0.0)
Requires-Dist: python-dateutil (>=2.8.2,<2.9.0)
Requires-Dist: pyyaml (>=6.0,<7.0)
Requires-Dist: typer (>=0.16.0,<1.0.0)
Requires-Dist: xtestrunner (>=1.8.5)
Project-URL: Documentation, https://seldomqa.github.io
Project-URL: Homepage, https://seldomqa.github.io
Project-URL: Repository, https://github.com/SeldomQA/seldom
